esaaf/__init__.py
esaaf/descript_aaf.py
esaaf/descript_interchange.py
esaaf/descript_xml.py
esaaf-1.0.2.dist-info/LICENSE
esaaf-1.0.2.dist-info/METADATA
esaaf-1.0.2.dist-info/WHEEL
esaaf-1.0.2.dist-info/top_level.txt
esaaf-1.0.2.dist-info/RECORD
