Metadata-Version: 2.2
Name: esaaf
Version: 1.0.2
Summary: A custom converter for Descript sequences from Premiere XML to Avid AAF
Author: Lawson Tanner
Author-email: lawson.tanner@endemolshine.com.au
Classifier: Programming Language :: Python :: 3
Classifier: License :: OSI Approved :: MIT License
Classifier: Operating System :: OS Independent
Requires-Python: >=3.7
License-File: LICENSE
Requires-Dist: pyaaf2>=1.7.1
Dynamic: author
Dynamic: author-email
Dynamic: classifier
Dynamic: requires-dist
Dynamic: requires-python
Dynamic: summary
